VisionKAN/.git/COMMIT_EDITMSG
VisionKAN/.git/FETCH_HEAD
VisionKAN/.git/HEAD
VisionKAN/.git/ORIG_HEAD
VisionKAN/.git/config
VisionKAN/.git/description
VisionKAN/.git/hooks/applypatch-msg.sample
VisionKAN/.git/hooks/commit-msg.sample
VisionKAN/.git/hooks/fsmonitor-watchman.sample
VisionKAN/.git/hooks/post-update.sample
VisionKAN/.git/hooks/pre-applypatch.sample
VisionKAN/.git/hooks/pre-commit.sample
VisionKAN/.git/hooks/pre-merge-commit.sample
VisionKAN/.git/hooks/pre-push.sample
VisionKAN/.git/hooks/pre-rebase.sample
VisionKAN/.git/hooks/pre-receive.sample
VisionKAN/.git/hooks/prepare-commit-msg.sample
VisionKAN/.git/hooks/push-to-checkout.sample
VisionKAN/.git/hooks/update.sample
VisionKAN/.git/index
VisionKAN/.git/info/exclude
VisionKAN/.git/logs/HEAD
VisionKAN/.git/logs/refs/heads/main
VisionKAN/.git/logs/refs/heads/patch-1
VisionKAN/.git/logs/refs/remotes/origin/HEAD
VisionKAN/.git/logs/refs/remotes/origin/main
VisionKAN/.git/logs/refs/remotes/origin/patch-1
VisionKAN/.git/objects/03/5758c4872124d834ee6e539c4b85b2a6be311c
VisionKAN/.git/objects/06/6241d382a6833daa9cd15cd1ed9f1d276e9351
VisionKAN/.git/objects/06/68b38d953d4aaff834ef30fcbb54ace8b44db8
VisionKAN/.git/objects/06/74abe9ee0925ae39a471b2bcda4ef468da405a
VisionKAN/.git/objects/09/cabeca13a688a93d1d3268c300759fa2c66325
VisionKAN/.git/objects/0c/3fdd176183c8a66b347340e4d84ad918cbc18c
VisionKAN/.git/objects/12/9a6e0aad0a851e986186c74ddb3ce96adaf5ee
VisionKAN/.git/objects/13/b30851219f73fd58967c40ff74387ffb424188
VisionKAN/.git/objects/15/12f01aeb2737c67d44e5a2de3daab934bc00d4
VisionKAN/.git/objects/15/882637c211157b37fd7eabb34894795520e0bb
VisionKAN/.git/objects/16/8c00f3102d915e4bc73d1034f91549ad22e428
VisionKAN/.git/objects/21/fbe556dd1106f6a79eb78fac39019b38d89519
VisionKAN/.git/objects/25/3f201824ad7beb456236e0b910d2c0a9d1df2d
VisionKAN/.git/objects/27/9af88c958e602fe7e7836555be28ab6b2dcb20
VisionKAN/.git/objects/29/ff87b50e72193eec1f7a4f5385f30d66f53613
visionkan-0.0.7.dist-info/LICENSE
visionkan-0.0.7.dist-info/METADATA
visionkan-0.0.7.dist-info/WHEEL
visionkan-0.0.7.dist-info/RECORD
