Metadata-Version: 2.1
Name: VisionKAN
Version: 0.0.7
Summary: Vision Transformers implemented using KAN layers
Home-page: https://github.com/chenziwenhaoshuai/Vision-KAN
License: MIT
Author: Saaketh Koundinya, Ziwen Chen
Author-email: three2saki@gmail.com
Requires-Python: >=3.6,<4.0
Classifier: License :: OSI Approved :: MIT License
Classifier: Programming Language :: Python :: 3
Classifier: Programming Language :: Python :: 3.6
Classifier: Programming Language :: Python :: 3.7
Classifier: Programming Language :: Python :: 3.8
Classifier: Programming Language :: Python :: 3.9
Classifier: Programming Language :: Python :: 3.10
Classifier: Programming Language :: Python :: 3.11
Classifier: Programming Language :: Python :: 3.12
Requires-Dist: timm (>=0.3.2)
Requires-Dist: torch (>=1.13.1)
Requires-Dist: torchvision (>=0.8.1)
Project-URL: Repository, https://github.com/chenziwenhaoshuai/Vision-KAN
